README.md
gameoflife.py
setup.py
Project1_Game_of_life.egg-info/PKG-INFO
Project1_Game_of_life.egg-info/SOURCES.txt
Project1_Game_of_life.egg-info/dependency_links.txt
Project1_Game_of_life.egg-info/requires.txt
Project1_Game_of_life.egg-info/top_level.txt