Metadata-Version: 1.0
Name: Project1-Game-of-life
Version: 1.2
Summary: Project for the course "Advanced Scientific Programming in Python", 23-27 March 2020, Uppsala University.
Home-page: https://github.com/rafael-mrden/Project1_Game-of-life
Author: Rafael Mrden
Author-email: rafael.mrdjen@gmail.com
License: BSD
Platform: UNKNOWN
